Libras/__init__.py
Libras/config.py
Libras/exception.py
Libras/mapping.py
Libras/registration.py
Libras/response.py
Libras/filter/__init__.py
Libras/filter/restful_filter.py
Libras/utils/__init__.py
libras-1.0.3.dist-info/LICENSE
libras-1.0.3.dist-info/METADATA
libras-1.0.3.dist-info/WHEEL
libras-1.0.3.dist-info/top_level.txt
libras-1.0.3.dist-info/RECORD
