Metadata-Version: 2.1
Name: libras
Version: 1.0.3
Summary: Based on the flask web framework
Home-page: https://github.com/barleyawn/libras
Author: barleyawn
Author-email: barleyawn@qq.com
License: UNKNOWN
Keywords: flask web restful
Platform: UNKNOWN
Classifier: Programming Language :: Python :: 3
Classifier: Operating System :: OS Independent
Classifier: License :: OSI Approved :: Apache Software License
Classifier: Framework :: Flask
